pytest_celery_py37/__init__.py
pytest_celery_py37/api/__init__.py
pytest_celery_py37/api/backend.py
pytest_celery_py37/api/base.py
pytest_celery_py37/api/broker.py
pytest_celery_py37/api/container.py
pytest_celery_py37/api/setup.py
pytest_celery_py37/api/worker.py
pytest_celery_py37/defaults.py
pytest_celery_py37/fixtures/__init__.py
pytest_celery_py37/fixtures/backend.py
pytest_celery_py37/fixtures/broker.py
pytest_celery_py37/fixtures/setup.py
pytest_celery_py37/fixtures/worker.py
pytest_celery_py37/plugin.py
pytest_celery_py37/vendors/__init__.py
pytest_celery_py37/vendors/localstack/__init__.py
pytest_celery_py37/vendors/localstack/api.py
pytest_celery_py37/vendors/localstack/container.py
pytest_celery_py37/vendors/localstack/defaults.py
pytest_celery_py37/vendors/localstack/fixtures.py
pytest_celery_py37/vendors/memcached/__init__.py
pytest_celery_py37/vendors/memcached/api.py
pytest_celery_py37/vendors/memcached/container.py
pytest_celery_py37/vendors/memcached/defaults.py
pytest_celery_py37/vendors/memcached/fixtures.py
pytest_celery_py37/vendors/rabbitmq/__init__.py
pytest_celery_py37/vendors/rabbitmq/api.py
pytest_celery_py37/vendors/rabbitmq/container.py
pytest_celery_py37/vendors/rabbitmq/defaults.py
pytest_celery_py37/vendors/rabbitmq/fixtures.py
pytest_celery_py37/vendors/redis/__init__.py
pytest_celery_py37/vendors/redis/backend/__init__.py
pytest_celery_py37/vendors/redis/backend/api.py
pytest_celery_py37/vendors/redis/backend/defaults.py
pytest_celery_py37/vendors/redis/backend/fixtures.py
pytest_celery_py37/vendors/redis/broker/__init__.py
pytest_celery_py37/vendors/redis/broker/api.py
pytest_celery_py37/vendors/redis/broker/defaults.py
pytest_celery_py37/vendors/redis/broker/fixtures.py
pytest_celery_py37/vendors/redis/container.py
pytest_celery_py37/vendors/redis/defaults.py
pytest_celery_py37/vendors/worker/Dockerfile
pytest_celery_py37/vendors/worker/__init__.py
pytest_celery_py37/vendors/worker/container.py
pytest_celery_py37-1.2.0.dist-info/LICENSE
pytest_celery_py37-1.2.0.dist-info/METADATA
pytest_celery_py37-1.2.0.dist-info/WHEEL
pytest_celery_py37-1.2.0.dist-info/entry_points.txt
pytest_celery_py37-1.2.0.dist-info/RECORD
