Metadata-Version: 2.1
Name: pytest-celery-py37
Version: 1.2.0
Summary: Pytest plugin for Celery (compatible with python 3.7)
Home-page: https://github.com/amirkazan/pytest-celery-py37
License: BSD-3-Clause
Keywords: pytest,celery
Author: Tomer Nosrati
Author-email: tomer.nosrati@gmail.com
Requires-Python: >=3.7,<4.0
Classifier: Development Status :: 5 - Production/Stable
Classifier: Framework :: Celery
Classifier: License :: OSI Approved :: BSD License
Classifier: Operating System :: OS Independent
Classifier: Programming Language :: Python
Classifier: Programming Language :: Python :: 3
Classifier: Programming Language :: Python :: 3.7
Classifier: Programming Language :: Python :: 3.8
Classifier: Programming Language :: Python :: 3.9
Classifier: Programming Language :: Python :: 3.10
Classifier: Programming Language :: Python :: 3.11
Classifier: Programming Language :: Python :: 3 :: Only
Classifier: Programming Language :: Python :: 3.12
Classifier: Programming Language :: Python :: 3.13
Classifier: Programming Language :: Python :: Implementation :: CPython
Classifier: Topic :: Software Development :: Testing
Provides-Extra: all
Provides-Extra: memcached
Provides-Extra: redis
Provides-Extra: sqs
Requires-Dist: boto3 ; extra == "all" or extra == "sqs"
Requires-Dist: botocore ; extra == "all" or extra == "sqs"
Requires-Dist: celery
Requires-Dist: debugpy (>=1.7.0,<2.0.0)
Requires-Dist: docker (>=6.1.3,<7.0.0)
Requires-Dist: kombu
Requires-Dist: psutil (>=7.0.0)
Requires-Dist: pytest-docker-tools (>=3.1.3)
Requires-Dist: python-memcached ; extra == "all" or extra == "memcached"
Requires-Dist: redis ; extra == "all" or extra == "redis"
Requires-Dist: setuptools (==68.0.0) ; python_full_version < "3.8.0"
Requires-Dist: setuptools (>=60.0.0,<75.0.0) ; python_version >= "3.8" and python_version < "3.9"
Requires-Dist: setuptools (>=75.8.0) ; python_version >= "3.9" and python_version < "4.0"
Requires-Dist: tenacity (>=8.2.3)
Requires-Dist: urllib3 (>=1.26.16,<2.0) ; extra == "all" or extra == "sqs"
